pygeofun/__init__.py
pygeofun/_version.py
geofun.cpython-310-x86_64-linux-gnu.so
pygeofun-0.0.14.dist-info/LICENSE
pygeofun-0.0.14.dist-info/METADATA
pygeofun-0.0.14.dist-info/WHEEL
pygeofun-0.0.14.dist-info/RECORD
