Metadata-Version: 2.1
Name: pygeofun
Version: 0.0.14
Summary: Geographic Functions: geodesics and rhumblines, orthodromes and loxodromes
Home-page: https://github.com/jrversteegh/geofun
Keywords: geodesic,rhumb line,loxodrome,orthodrome,distance,azimuth
Author: Jaap Versteegh
Author-email: j.r.versteegh@gmail.com
Requires-Python: >=3.9,<4.0
Classifier: License :: OSI Approved :: MIT License
Classifier: Operating System :: OS Independent
Classifier: Programming Language :: Python :: 3
Classifier: Programming Language :: Python :: 3.9
Classifier: Programming Language :: Python :: 3.10
Classifier: Programming Language :: Python :: 3.11
Classifier: Programming Language :: Python :: 3.12
Classifier: Topic :: Scientific/Engineering :: GIS
Provides-Extra: docs
Project-URL: Repository, https://github.com/jrversteegh/geofun
